mcp_amazon_paapi/__init__.py
mcp_amazon_paapi/server.py
mcp_amazon_paapi/service.py
mcp_amazon_paapi/_vendor/__init__.py
mcp_amazon_paapi/_vendor/paapi5_python_sdk/__init__.py
mcp_amazon_paapi/_vendor/paapi5_python_sdk/api_client.py
mcp_amazon_paapi/_vendor/paapi5_python_sdk/configuration.py
mcp_amazon_paapi/_vendor/paapi5_python_sdk/rest.py
mcp_amazon_paapi/_vendor/paapi5_python_sdk/api/__init__.py
mcp_amazon_paapi/_vendor/paapi5_python_sdk/api/default_api.py
mcp_amazon_paapi/_vendor/paapi5_python_sdk/auth/__init__.py
mcp_amazon_paapi/_vendor/paapi5_python_sdk/auth/sign_helper.py
mcp_amazon_paapi/_vendor/paapi5_python_sdk/models/__init__.py
mcp_amazon_paapi/_vendor/paapi5_python_sdk/models/availability.py
mcp_amazon_paapi/_vendor/paapi5_python_sdk/models/big_decimal.py
mcp_amazon_paapi/_vendor/paapi5_python_sdk/models/browse_node.py
mcp_amazon_paapi/_vendor/paapi5_python_sdk/models/browse_node_ancestor.py
mcp_amazon_paapi/_vendor/paapi5_python_sdk/models/browse_node_child.py
mcp_amazon_paapi/_vendor/paapi5_python_sdk/models/browse_node_info.py
mcp_amazon_paapi/_vendor/paapi5_python_sdk/models/browse_nodes_result.py
mcp_amazon_paapi/_vendor/paapi5_python_sdk/models/by_line_info.py
mcp_amazon_paapi/_vendor/paapi5_python_sdk/models/classifications.py
mcp_amazon_paapi/_vendor/paapi5_python_sdk/models/condition.py
mcp_amazon_paapi/_vendor/paapi5_python_sdk/models/content_info.py
mcp_amazon_paapi/_vendor/paapi5_python_sdk/models/content_rating.py
mcp_amazon_paapi/_vendor/paapi5_python_sdk/models/contributor.py
mcp_amazon_paapi/_vendor/paapi5_python_sdk/models/customer_reviews.py
mcp_amazon_paapi/_vendor/paapi5_python_sdk/models/deal_details.py
mcp_amazon_paapi/_vendor/paapi5_python_sdk/models/delivery_flag.py
mcp_amazon_paapi/_vendor/paapi5_python_sdk/models/dimension_based_attribute.py
mcp_amazon_paapi/_vendor/paapi5_python_sdk/models/duration_price.py
mcp_amazon_paapi/_vendor/paapi5_python_sdk/models/error_data.py
mcp_amazon_paapi-0.4.0.dist-info/METADATA
mcp_amazon_paapi-0.4.0.dist-info/WHEEL
mcp_amazon_paapi-0.4.0.dist-info/entry_points.txt
mcp_amazon_paapi-0.4.0.dist-info/top_level.txt
mcp_amazon_paapi-0.4.0.dist-info/RECORD
