Metadata-Version: 2.4
Name: mcp-amazon-paapi
Version: 0.4.0
Summary: A Model Context Protocol (MCP) service for Amazon Product Advertising API integration.
Author: JadeMind GmbH 
Maintainer-email: Andreas Katzian <support@jademind.com>
License-Expression: MIT
Project-URL: Homepage, https://github.com/jademind/mcp-amazon-paapi
Project-URL: Repository, https://github.com/jademind/mcp-amazon-paapi
Project-URL: Issues, https://github.com/jademind/mcp-amazon-paapi/issues
Keywords: mcp,amazon,affiliate,product advertising
Classifier: Development Status :: 4 - Beta
Classifier: Intended Audience :: End Users/Desktop
Classifier: Programming Language :: Python :: 3
Classifier: Programming Language :: Python :: 3.11
Requires-Python: >=3.11
Requires-Dist: httpx>=0.28.1
Requires-Dist: mcp[cli]>=1.9.4
Requires-Dist: urllib3>=1.15.1
Requires-Dist: certifi>=14.05.14
Requires-Dist: six>=1.10
Requires-Dist: python-dateutil>=2.5.3
